HummingbirdJoystickCalculator.py
hummingbird_joystick_calculator.py
hummingbird_joystick_calculator/__init__.py
hummingbird_joystick_calculator/__main__.py
hummingbird_joystick_calculator/cli.py
hummingbird_joystick_calculator-0.0.6.dist-info/AUTHORS.rst
hummingbird_joystick_calculator-0.0.6.dist-info/LICENSE
hummingbird_joystick_calculator-0.0.6.dist-info/METADATA
hummingbird_joystick_calculator-0.0.6.dist-info/WHEEL
hummingbird_joystick_calculator-0.0.6.dist-info/entry_points.txt
hummingbird_joystick_calculator-0.0.6.dist-info/top_level.txt
hummingbird_joystick_calculator-0.0.6.dist-info/RECORD
