Metadata-Version: 2.1
Name: hummingbird-joystick-calculator
Version: 0.0.6
Summary: Calculator for the hummingbird_joystick package converting xy coordinates from the joystick to left/right motor speeds.
Home-page: https://github.com/fmorton/python-hummingbird-joystick-calculator
Author: Frank Morton
Author-email: fmorton@base2inc.com
License: MIT
Project-URL: Documentation, https://python-hummingbird-joystick-calculator.readthedocs.io/
Project-URL: Changelog, https://python-hummingbird-joystick-calculator.readthedocs.io/en/latest/changelog.html
Project-URL: Issue Tracker, https://github.com/fmorton/python-hummingbird-joystick-calculator/issues
Classifier: Development Status :: 5 - Production/Stable
Classifier: Intended Audience :: Developers
Classifier: License :: OSI Approved :: MIT License
Classifier: Operating System :: Unix
Classifier: Operating System :: POSIX
Classifier: Operating System :: Microsoft :: Windows
Classifier: Programming Language :: Python
Classifier: Programming Language :: Python :: 3
Classifier: Programming Language :: Python :: 3 :: Only
Classifier: Programming Language :: Python :: 3.7
Classifier: Programming Language :: Python :: 3.8
Classifier: Programming Language :: Python :: 3.9
Classifier: Programming Language :: Python :: 3.10
Classifier: Programming Language :: Python :: Implementation :: CPython
Classifier: Programming Language :: Python :: Implementation :: PyPy
Classifier: Topic :: Utilities
Requires-Python: >=3.7
License-File: LICENSE
License-File: AUTHORS.rst
